<?xml version="1.0" encoding="UTF-8"?><ab xmlns="http://www.tei-c.org/ns/1.0" type="dDay" xml:id="g1795-02-27"><date xmlns="http://www.tei-c.org/ns/1.0" when="1795-02-27">27. F.</date><ref xmlns="http://www.tei-c.org/ns/1.0" type="dWrote" subtype="other" target="/works/unkn01.html">Proofs, F &amp; G</ref>. <seg xmlns="http://www.tei-c.org/ns/1.0" type="dMeeting" subtype="CG"><persName xmlns="http://www.tei-c.org/ns/1.0" ref="/people/JEN02.html">Mrs Jennings</persName> calls</seg>: <seg xmlns="http://www.tei-c.org/ns/1.0" type="dMeal" subtype="D"><persName xmlns="http://www.tei-c.org/ns/1.0" ref="/people/MAR01.html"><placeName xmlns="http://www.tei-c.org/ns/1.0" type="venue">M.</placeName></persName> dines</seg>: <seg xmlns="http://www.tei-c.org/ns/1.0" type="dMeal" subtype="Ta">tea <persName xmlns="http://www.tei-c.org/ns/1.0" ref="/people/FRE01.html"><placeName xmlns="http://www.tei-c.org/ns/1.0" type="venue">Frend's</placeName></persName>, w. <persName xmlns="http://www.tei-c.org/ns/1.0" ref="/people/HOL01.html">H<hi xmlns="http://www.tei-c.org/ns/1.0" rend="sup">t</hi></persName>, <persName xmlns="http://www.tei-c.org/ns/1.0" ref="/people/LOS01.html">Losh</persName>, <persName xmlns="http://www.tei-c.org/ns/1.0" ref="/people/TWE01.html">Tweddel</persName>, <persName xmlns="http://www.tei-c.org/ns/1.0" ref="/people/RAI03.html">Jona<hi xmlns="http://www.tei-c.org/ns/1.0" rend="sup">n</hi>
                  Raine</persName>, <persName xmlns="http://www.tei-c.org/ns/1.0">Edwards</persName>, <persName xmlns="http://www.tei-c.org/ns/1.0" ref="/people/WOR01.html">Wordsworth, </persName><persName xmlns="http://www.tei-c.org/ns/1.0" ref="/people/HIG01.html">Higgins</persName>, 
                     <persName xmlns="http://www.tei-c.org/ns/1.0">French</persName> &amp; <persName xmlns="http://www.tei-c.org/ns/1.0" ref="/people/DYE01.html">Dyer</persName>, <emph xmlns="http://www.tei-c.org/ns/1.0" rend="deleted">//</emph></seg>: <seg xmlns="http://www.tei-c.org/ns/1.0" type="dMeal" subtype="S">sup at
                     <persName xmlns="http://www.tei-c.org/ns/1.0" ref="/people/JEN01|JEN02.html"><placeName xmlns="http://www.tei-c.org/ns/1.0" type="venue">Jennings's</placeName></persName></seg>.</ab>