<?xml version="1.0" encoding="UTF-8"?><ab xmlns="http://www.tei-c.org/ns/1.0" type="dDay" xml:id="g1795-06-07"><date xmlns="http://www.tei-c.org/ns/1.0" when="1795-06-07">June 7. Su.</date><seg xmlns="http://www.tei-c.org/ns/1.0" type="dMeal" subtype="BG"><persName xmlns="http://www.tei-c.org/ns/1.0" ref="/people/SMI01.html">Smith</persName> breakfasts; <seg xmlns="http://www.tei-c.org/ns/1.0" type="dMeeting" subtype="Adv">adv.
                        <persName xmlns="http://www.tei-c.org/ns/1.0" ref="/people/MOO02.html">M Moore</persName></seg></seg>: <seg xmlns="http://www.tei-c.org/ns/1.0" type="dMeal" subtype="D">dine at <persName xmlns="http://www.tei-c.org/ns/1.0" ref="/people/KIN01.html"><placeName xmlns="http://www.tei-c.org/ns/1.0" type="venue">King's</placeName></persName>, w. <persName xmlns="http://www.tei-c.org/ns/1.0">Butler</persName></seg> : <seg xmlns="http://www.tei-c.org/ns/1.0" type="dMeal" subtype="S">sup at <persName xmlns="http://www.tei-c.org/ns/1.0" ref="/people/HOL01.html"><placeName xmlns="http://www.tei-c.org/ns/1.0" type="venue">Hts</placeName></persName>; <seg xmlns="http://www.tei-c.org/ns/1.0" type="dMeeting" subtype="Adv">adv. <persName xmlns="http://www.tei-c.org/ns/1.0" ref="/people/RIC05.html">G Richter</persName></seg></seg>. <add xmlns="http://www.tei-c.org/ns/1.0"><emph xmlns="http://www.tei-c.org/ns/1.0" rend="other"><seg xmlns="http://www.tei-c.org/ns/1.0" type="dMeeting" subtype="Adv">adv. <persName xmlns="http://www.tei-c.org/ns/1.0">Robertson</persName></seg>: <seg xmlns="http://www.tei-c.org/ns/1.0" type="dMeeting" subtype="See">see <persName xmlns="http://www.tei-c.org/ns/1.0" ref="/people/KEM01.html">C Kemble</persName></seg></emph></add>. <emph xmlns="http://www.tei-c.org/ns/1.0" rend="red"><ref xmlns="http://www.tei-c.org/ns/1.0" type="dEvent" subtype="Publ" target="/events/pu0070.html"><placeName xmlns="http://www.tei-c.org/ns/1.0">Luxemburgh</placeName> taken</ref>.</emph></ab>