<?xml version="1.0" encoding="UTF-8"?><ab xmlns="http://www.tei-c.org/ns/1.0" type="dDay" xml:id="g1795-04-25"><date xmlns="http://www.tei-c.org/ns/1.0" when="1795-04-25">25. Sa.</date><seg xmlns="http://www.tei-c.org/ns/1.0" type="dMeeting" subtype="C">Call on <persName xmlns="http://www.tei-c.org/ns/1.0" ref="/people/ROB01.html"><placeName xmlns="http://www.tei-c.org/ns/1.0" type="venue">Robinson</placeName></persName></seg>, &amp; <seg xmlns="http://www.tei-c.org/ns/1.0" type="dMeeting" subtype="C"><persName xmlns="http://www.tei-c.org/ns/1.0" ref="/people/TAY05.html" type="nah"><placeName xmlns="http://www.tei-c.org/ns/1.0" type="venue">T Taylor</placeName></persName> nah</seg>: <seg xmlns="http://www.tei-c.org/ns/1.0" type="dMeal" subtype="D">dine at <persName xmlns="http://www.tei-c.org/ns/1.0" ref="/people/GER01.html"><placeName xmlns="http://www.tei-c.org/ns/1.0" type="venue">Gerald's</placeName></persName>, w. <persName xmlns="http://www.tei-c.org/ns/1.0" ref="/people/KIN01.html">King</persName> &amp; <persName xmlns="http://www.tei-c.org/ns/1.0">
                  ladies</persName></seg>. <ref xmlns="http://www.tei-c.org/ns/1.0" type="dWrote" subtype="letter">Write to <persName xmlns="http://www.tei-c.org/ns/1.0" ref="/people/MAR01.html">M </persName>on
                  publication</ref>.</ab>