<?xml version="1.0" encoding="UTF-8"?><ab xmlns="http://www.tei-c.org/ns/1.0" type="dDay" subtype="NotLon" xml:id="g1795-06-23"><date xmlns="http://www.tei-c.org/ns/1.0" when="1795-06-23">23. Tu.</date><seg xmlns="http://www.tei-c.org/ns/1.0" type="dMeal" subtype="D">Dine at <placeName xmlns="http://www.tei-c.org/ns/1.0">Hatton</placeName>, w. <persName xmlns="http://www.tei-c.org/ns/1.0" ref="/people/DOR02.html">lord Dormer
                     &amp; son</persName>, <persName xmlns="http://www.tei-c.org/ns/1.0" ref="/people/GRE02.html">Greatheed</persName>,
                     <persName xmlns="http://www.tei-c.org/ns/1.0">Eyre</persName>, <persName xmlns="http://www.tei-c.org/ns/1.0">Wills</persName>,
                  <persName xmlns="http://www.tei-c.org/ns/1.0">Howel</persName>, <persName xmlns="http://www.tei-c.org/ns/1.0">Mawley</persName>, <persName xmlns="http://www.tei-c.org/ns/1.0" ref="/people/LAM05.html">Lambes</persName>, <persName xmlns="http://www.tei-c.org/ns/1.0">Bradley</persName> &amp; <persName xmlns="http://www.tei-c.org/ns/1.0">Howes
                     resident</persName></seg>.</ab>