<?xml version="1.0" encoding="UTF-8"?><ab xmlns="http://www.tei-c.org/ns/1.0" type="dDay" xml:id="g1795-05-06"><date xmlns="http://www.tei-c.org/ns/1.0" when="1795-05-06">6. W.</date><ref xmlns="http://www.tei-c.org/ns/1.0" type="dEvent" subtype="other">Cha. of <persName xmlns="http://www.tei-c.org/ns/1.0" ref="/people/GER01.html">Gerald</persName></ref>: <ref xmlns="http://www.tei-c.org/ns/1.0" type="dWrote" subtype="revised" target="/works/poli01.html">revise</ref>. <seg xmlns="http://www.tei-c.org/ns/1.0" type="dMeeting" subtype="C">Call on <persName xmlns="http://www.tei-c.org/ns/1.0" ref="/people/DAV02.html"><placeName xmlns="http://www.tei-c.org/ns/1.0" type="venue">Davis</placeName></persName></seg>, <seg xmlns="http://www.tei-c.org/ns/1.0" type="dMeeting" subtype="C"><persName xmlns="http://www.tei-c.org/ns/1.0" ref="/people/FER01.html"><placeName xmlns="http://www.tei-c.org/ns/1.0" type="venue">Fergusson</placeName></persName></seg>, <seg xmlns="http://www.tei-c.org/ns/1.0" type="dMeeting" subtype="C"><persName xmlns="http://www.tei-c.org/ns/1.0" type="nah"><placeName xmlns="http://www.tei-c.org/ns/1.0" type="venue">Gray</placeName></persName> nah</seg>, &amp; <seg xmlns="http://www.tei-c.org/ns/1.0" type="dMeeting" subtype="C"><persName xmlns="http://www.tei-c.org/ns/1.0" ref="/people/HOL02.html"><placeName xmlns="http://www.tei-c.org/ns/1.0" type="venue">B. Hollis</placeName></persName></seg>: <seg xmlns="http://www.tei-c.org/ns/1.0" type="dMeal" subtype="D">dine at <persName xmlns="http://www.tei-c.org/ns/1.0" ref="/people/KIN01.html"><placeName xmlns="http://www.tei-c.org/ns/1.0" type="venue">King's </placeName></persName>w. <persName xmlns="http://www.tei-c.org/ns/1.0">Buller contr</persName></seg>.: <seg xmlns="http://www.tei-c.org/ns/1.0" type="dMeal" subtype="Ta">tea <persName xmlns="http://www.tei-c.org/ns/1.0" ref="/people/HOL01.html"><placeName xmlns="http://www.tei-c.org/ns/1.0" type="venue">Hts</placeName></persName>, w. <persName xmlns="http://www.tei-c.org/ns/1.0" ref="/people/KIN01.html">Kings</persName>, <persName xmlns="http://www.tei-c.org/ns/1.0" ref="/people/FOU01.html">Foulkes's</persName>, <persName xmlns="http://www.tei-c.org/ns/1.0" ref="/people/BAT01.html">Battys</persName>, <persName xmlns="http://www.tei-c.org/ns/1.0" ref="/people/BAN03.html">Banks{,}</persName><persName xmlns="http://www.tei-c.org/ns/1.0">Dennis</persName>, <persName xmlns="http://www.tei-c.org/ns/1.0" ref="/people/ALD02.html">A Alderson</persName> &amp;
                     <persName xmlns="http://www.tei-c.org/ns/1.0">miss Winal</persName></seg>. <ref xmlns="http://www.tei-c.org/ns/1.0" type="dText" subtype="read" target="/bibl/te0284.html">Virgil, 186</ref>.</ab>