<?xml version="1.0" encoding="UTF-8"?><ab xmlns="http://www.tei-c.org/ns/1.0" type="dDay" xml:id="g1795-09-15"><date xmlns="http://www.tei-c.org/ns/1.0" when="1795-09-15">15. Tu. </date><ref xmlns="http://www.tei-c.org/ns/1.0" type="dWrote" subtype="revised" target="/works/poli01.html">Revise</ref>: <ref xmlns="http://www.tei-c.org/ns/1.0" type="dText" subtype="read" target="/bibl/te0606.html">Prim Wife, acts 1, 2, 3</ref>. <seg xmlns="http://www.tei-c.org/ns/1.0" type="dMeeting" subtype="C">Call on
                     <persName xmlns="http://www.tei-c.org/ns/1.0" ref="/people/FEN01.html"><placeName xmlns="http://www.tei-c.org/ns/1.0" type="venue">Fenwick</placeName></persName></seg>: <seg xmlns="http://www.tei-c.org/ns/1.0" type="dMeeting" subtype="other"><orgName xmlns="http://www.tei-c.org/ns/1.0">Philomaths</orgName>, <seg xmlns="http://www.tei-c.org/ns/1.0" type="dTopic">means of reform</seg></seg>.</ab>