<?xml version="1.0" encoding="UTF-8"?><listPerson xmlns="http://www.tei-c.org/ns/1.0"><person xmlns="http://www.tei-c.org/ns/1.0" xml:id="FAW02" sex="2"><persName xmlns="http://www.tei-c.org/ns/1.0"><roleName xmlns="http://www.tei-c.org/ns/1.0"/><forename xmlns="http://www.tei-c.org/ns/1.0">Charlotte</forename><surname xmlns="http://www.tei-c.org/ns/1.0">Fawcett</surname><addName xmlns="http://www.tei-c.org/ns/1.0">née French</addName></persName><birth xmlns="http://www.tei-c.org/ns/1.0" when="1000"><placeName xmlns="http://www.tei-c.org/ns/1.0"/></birth><death xmlns="http://www.tei-c.org/ns/1.0" when="1824-06-18"/><occupation xmlns="http://www.tei-c.org/ns/1.0"/><note xmlns="http://www.tei-c.org/ns/1.0" type="editorial"><p xmlns="http://www.tei-c.org/ns/1.0">According to her husband's <title xmlns="http://www.tei-c.org/ns/1.0">DNB</title> entry,  Charlotte, neé French, married <persName xmlns="http://www.tei-c.org/ns/1.0" key="FAW01">Joseph Fawcett</persName> in September 1782.</p><p xmlns="http://www.tei-c.org/ns/1.0">Godwin recorded her death - the year being confirmed in the<title xmlns="http://www.tei-c.org/ns/1.0">DNB</title>.</p></note><bibl xmlns="http://www.tei-c.org/ns/1.0" type="other"><title xmlns="http://www.tei-c.org/ns/1.0">DNB</title>, 'Joseph Fawcett'.</bibl><ab xmlns="http://www.tei-c.org/ns/1.0" type="appearancesInDiary"><ab xmlns="http://www.tei-c.org/ns/1.0" n="1788"/><ab xmlns="http://www.tei-c.org/ns/1.0" n="1789"/><ab xmlns="http://www.tei-c.org/ns/1.0" n="1790"/><ab xmlns="http://www.tei-c.org/ns/1.0" n="1791"/><ab xmlns="http://www.tei-c.org/ns/1.0" n="1792"/><ab xmlns="http://www.tei-c.org/ns/1.0" n="1793"><date xmlns="http://www.tei-c.org/ns/1.0" when="1793-06-21" n="venue" type="ah"/><date xmlns="http://www.tei-c.org/ns/1.0" when="1793-07-22" n="venue" type="ah"/><date xmlns="http://www.tei-c.org/ns/1.0" when="1793-08-12" n="venue" type="ah"/><date xmlns="http://www.tei-c.org/ns/1.0" when="1793-09-17" n="venue" type="ah"/><date xmlns="http://www.tei-c.org/ns/1.0" when="1793-10-16" n="venue" type="ah"/></ab><ab xmlns="http://www.tei-c.org/ns/1.0" n="1794"><date xmlns="http://www.tei-c.org/ns/1.0" when="1794-04-22" n="venue" type="ah"/><date xmlns="http://www.tei-c.org/ns/1.0" when="1794-05-22" n="venue" type="ah"/><date xmlns="http://www.tei-c.org/ns/1.0" when="1794-06-16" n="venue" type="ah"/><date xmlns="http://www.tei-c.org/ns/1.0" when="1794-07-21" n="venue" type="ah"/><date xmlns="http://www.tei-c.org/ns/1.0" when="1794-07-31" n="venue" type="ah"/></ab><ab xmlns="http://www.tei-c.org/ns/1.0" n="1795"><date xmlns="http://www.tei-c.org/ns/1.0" when="1795-07-09" n="venue" type="ah"/><date xmlns="http://www.tei-c.org/ns/1.0" when="1795-07-10" n="venue" type="ah"/></ab><ab xmlns="http://www.tei-c.org/ns/1.0" n="1796"><date xmlns="http://www.tei-c.org/ns/1.0" when="1796-05-29" n="venue" type="ah"/></ab><ab xmlns="http://www.tei-c.org/ns/1.0" n="1797"><date xmlns="http://www.tei-c.org/ns/1.0" when="1797-07-21" n="notVenue" type="ah"/><date xmlns="http://www.tei-c.org/ns/1.0" when="1797-12-29" n="notVenue" type="ah"/></ab><ab xmlns="http://www.tei-c.org/ns/1.0" n="1798"><date xmlns="http://www.tei-c.org/ns/1.0" when="1798-01-11" n="notVenue" type="ah"/></ab><ab xmlns="http://www.tei-c.org/ns/1.0" n="1799"><date xmlns="http://www.tei-c.org/ns/1.0" when="1799-04-09" n="notVenue" type="ah"/><date xmlns="http://www.tei-c.org/ns/1.0" when="1799-05-07" n="venue" type="ah"/></ab><ab xmlns="http://www.tei-c.org/ns/1.0" n="1800"/><ab xmlns="http://www.tei-c.org/ns/1.0" n="1801"/><ab xmlns="http://www.tei-c.org/ns/1.0" n="1802"/><ab xmlns="http://www.tei-c.org/ns/1.0" n="1803"/><ab xmlns="http://www.tei-c.org/ns/1.0" n="1804"/><ab xmlns="http://www.tei-c.org/ns/1.0" n="1805"/><ab xmlns="http://www.tei-c.org/ns/1.0" n="1806"/><ab xmlns="http://www.tei-c.org/ns/1.0" n="1807"/><ab xmlns="http://www.tei-c.org/ns/1.0" n="1808"/><ab xmlns="http://www.tei-c.org/ns/1.0" n="1809"/><ab xmlns="http://www.tei-c.org/ns/1.0" n="1810"/><ab xmlns="http://www.tei-c.org/ns/1.0" n="1811"/><ab xmlns="http://www.tei-c.org/ns/1.0" n="1812"/><ab xmlns="http://www.tei-c.org/ns/1.0" n="1813"/><ab xmlns="http://www.tei-c.org/ns/1.0" n="1814"/><ab xmlns="http://www.tei-c.org/ns/1.0" n="1815"/><ab xmlns="http://www.tei-c.org/ns/1.0" n="1816"/><ab xmlns="http://www.tei-c.org/ns/1.0" n="1817"/><ab xmlns="http://www.tei-c.org/ns/1.0" n="1818"/><ab xmlns="http://www.tei-c.org/ns/1.0" n="1819"/><ab xmlns="http://www.tei-c.org/ns/1.0" n="1820"/><ab xmlns="http://www.tei-c.org/ns/1.0" n="1821"/><ab xmlns="http://www.tei-c.org/ns/1.0" n="1822"/><ab xmlns="http://www.tei-c.org/ns/1.0" n="1823"/><ab xmlns="http://www.tei-c.org/ns/1.0" n="1824"><date xmlns="http://www.tei-c.org/ns/1.0" when="1824-06-18" n="notVenue" type="ah"/></ab><ab xmlns="http://www.tei-c.org/ns/1.0" n="1825"/><ab xmlns="http://www.tei-c.org/ns/1.0" n="1826"/><ab xmlns="http://www.tei-c.org/ns/1.0" n="1827"/><ab xmlns="http://www.tei-c.org/ns/1.0" n="1828"/><ab xmlns="http://www.tei-c.org/ns/1.0" n="1829"/><ab xmlns="http://www.tei-c.org/ns/1.0" n="1830"/><ab xmlns="http://www.tei-c.org/ns/1.0" n="1831"/><ab xmlns="http://www.tei-c.org/ns/1.0" n="1832"/><ab xmlns="http://www.tei-c.org/ns/1.0" n="1833"/><ab xmlns="http://www.tei-c.org/ns/1.0" n="1834"/><ab xmlns="http://www.tei-c.org/ns/1.0" n="1835"/><ab xmlns="http://www.tei-c.org/ns/1.0" n="1836"/></ab></person></listPerson>