<?xml version="1.0" encoding="UTF-8"?><listPerson xmlns="http://www.tei-c.org/ns/1.0"><person xmlns="http://www.tei-c.org/ns/1.0" xml:id="GIF01" sex="1"><persName xmlns="http://www.tei-c.org/ns/1.0"><roleName xmlns="http://www.tei-c.org/ns/1.0"/><forename xmlns="http://www.tei-c.org/ns/1.0">William</forename><surname xmlns="http://www.tei-c.org/ns/1.0">Gifford</surname><addName xmlns="http://www.tei-c.org/ns/1.0"/></persName><birth xmlns="http://www.tei-c.org/ns/1.0" when="1756-04"><placeName xmlns="http://www.tei-c.org/ns/1.0"/></birth><death xmlns="http://www.tei-c.org/ns/1.0" when="1826-12-31"/><occupation xmlns="http://www.tei-c.org/ns/1.0">satirist</occupation><occupation xmlns="http://www.tei-c.org/ns/1.0">editor</occupation><note xmlns="http://www.tei-c.org/ns/1.0" type="editorial"><p xmlns="http://www.tei-c.org/ns/1.0">Godwin records his death and there are two contacts in 1818 and 1820.
    It seems likely that the 1820 contact was a case of Godwin sending Gifford a copy of his work on Population to be reviewed in the <title xmlns="http://www.tei-c.org/ns/1.0">Quarterly Review</title>, 
    which Gifford edited. Although a Tory periodical, and although Gifford had been a writer for and editor of the <title xmlns="http://www.tei-c.org/ns/1.0">Anti-Jacobin Review</title>, Godwin probably 
   hoped he would get a more sympathetic reception than he would from the <title xmlns="http://www.tei-c.org/ns/1.0">Edinburgh Review</title>, given its dominance by the political economists. In fact, he fared little better.</p></note><bibl xmlns="http://www.tei-c.org/ns/1.0" type="other"><title xmlns="http://www.tei-c.org/ns/1.0">DNB</title></bibl><bibl xmlns="http://www.tei-c.org/ns/1.0" type="journalism"><title xmlns="http://www.tei-c.org/ns/1.0">Quarterly Review</title>1821.</bibl><ab xmlns="http://www.tei-c.org/ns/1.0" type="appearancesInDiary"><ab xmlns="http://www.tei-c.org/ns/1.0" n="1788"/><ab xmlns="http://www.tei-c.org/ns/1.0" n="1789"/><ab xmlns="http://www.tei-c.org/ns/1.0" n="1790"/><ab xmlns="http://www.tei-c.org/ns/1.0" n="1791"/><ab xmlns="http://www.tei-c.org/ns/1.0" n="1792"/><ab xmlns="http://www.tei-c.org/ns/1.0" n="1793"/><ab xmlns="http://www.tei-c.org/ns/1.0" n="1794"/><ab xmlns="http://www.tei-c.org/ns/1.0" n="1795"/><ab xmlns="http://www.tei-c.org/ns/1.0" n="1796"/><ab xmlns="http://www.tei-c.org/ns/1.0" n="1797"/><ab xmlns="http://www.tei-c.org/ns/1.0" n="1798"/><ab xmlns="http://www.tei-c.org/ns/1.0" n="1799"/><ab xmlns="http://www.tei-c.org/ns/1.0" n="1800"/><ab xmlns="http://www.tei-c.org/ns/1.0" n="1801"/><ab xmlns="http://www.tei-c.org/ns/1.0" n="1802"/><ab xmlns="http://www.tei-c.org/ns/1.0" n="1803"/><ab xmlns="http://www.tei-c.org/ns/1.0" n="1804"/><ab xmlns="http://www.tei-c.org/ns/1.0" n="1805"/><ab xmlns="http://www.tei-c.org/ns/1.0" n="1806"/><ab xmlns="http://www.tei-c.org/ns/1.0" n="1807"/><ab xmlns="http://www.tei-c.org/ns/1.0" n="1808"/><ab xmlns="http://www.tei-c.org/ns/1.0" n="1809"/><ab xmlns="http://www.tei-c.org/ns/1.0" n="1810"/><ab xmlns="http://www.tei-c.org/ns/1.0" n="1811"/><ab xmlns="http://www.tei-c.org/ns/1.0" n="1812"/><ab xmlns="http://www.tei-c.org/ns/1.0" n="1813"/><ab xmlns="http://www.tei-c.org/ns/1.0" n="1814"/><ab xmlns="http://www.tei-c.org/ns/1.0" n="1815"/><ab xmlns="http://www.tei-c.org/ns/1.0" n="1816"/><ab xmlns="http://www.tei-c.org/ns/1.0" n="1817"/><ab xmlns="http://www.tei-c.org/ns/1.0" n="1818"><date xmlns="http://www.tei-c.org/ns/1.0" when="1818-05-04" n="notVenue" type="ah"/></ab><ab xmlns="http://www.tei-c.org/ns/1.0" n="1819"/><ab xmlns="http://www.tei-c.org/ns/1.0" n="1820"><date xmlns="http://www.tei-c.org/ns/1.0" when="1820-10-30" n="notVenue" type="ah"/></ab><ab xmlns="http://www.tei-c.org/ns/1.0" n="1821"/><ab xmlns="http://www.tei-c.org/ns/1.0" n="1822"/><ab xmlns="http://www.tei-c.org/ns/1.0" n="1823"/><ab xmlns="http://www.tei-c.org/ns/1.0" n="1824"/><ab xmlns="http://www.tei-c.org/ns/1.0" n="1825"/><ab xmlns="http://www.tei-c.org/ns/1.0" n="1826"><date xmlns="http://www.tei-c.org/ns/1.0" when="1826-12-31" n="notVenue" type="ah"/></ab><ab xmlns="http://www.tei-c.org/ns/1.0" n="1827"/><ab xmlns="http://www.tei-c.org/ns/1.0" n="1828"/><ab xmlns="http://www.tei-c.org/ns/1.0" n="1829"/><ab xmlns="http://www.tei-c.org/ns/1.0" n="1830"/><ab xmlns="http://www.tei-c.org/ns/1.0" n="1831"/><ab xmlns="http://www.tei-c.org/ns/1.0" n="1832"/><ab xmlns="http://www.tei-c.org/ns/1.0" n="1833"/><ab xmlns="http://www.tei-c.org/ns/1.0" n="1834"/><ab xmlns="http://www.tei-c.org/ns/1.0" n="1835"/><ab xmlns="http://www.tei-c.org/ns/1.0" n="1836"/></ab></person></listPerson>