<?xml version="1.0" encoding="UTF-8"?><listPerson xmlns="http://www.tei-c.org/ns/1.0"><person xmlns="http://www.tei-c.org/ns/1.0" xml:id="HAL02" sex="2"><persName xmlns="http://www.tei-c.org/ns/1.0"><roleName xmlns="http://www.tei-c.org/ns/1.0"/><forename xmlns="http://www.tei-c.org/ns/1.0">Mary</forename><surname xmlns="http://www.tei-c.org/ns/1.0">Cossley Hall</surname><addName xmlns="http://www.tei-c.org/ns/1.0"/></persName><birth xmlns="http://www.tei-c.org/ns/1.0" when="1000"><placeName xmlns="http://www.tei-c.org/ns/1.0">Jamaica</placeName></birth><death xmlns="http://www.tei-c.org/ns/1.0" when="1844"/><occupation xmlns="http://www.tei-c.org/ns/1.0"/><note xmlns="http://www.tei-c.org/ns/1.0" type="editorial">Mary Crossley Hall was the sister of Mrs Somerville Wood, with whom she lived. She was devoted 
    to Mrs Wood's daughter (who became Mrs Leicester Stanhope). Halls linked to Wood and to Stanhope 
    are coded as Mary Hall.  It is possible that this might confuse entries for her with those for her brother, 
    Thomas James Hall, b. 5 Dec 1788, who became chief magistrate of  the Bow Steet Police Court - and 
    who prior to that seems to have been  Advocate General of Jamaica 1819. He returned to England and 
    married Agnes Carr. The absence of 'Miss' before 'Hall' does not signify since Godwin does not 
    distinguish his contacts consistently in this way.
    
    See <title xmlns="http://www.tei-c.org/ns/1.0">New Monthly Belle Assembleé</title> (1844) p. 164. 
  </note><ab xmlns="http://www.tei-c.org/ns/1.0" type="appearancesInDiary"><ab xmlns="http://www.tei-c.org/ns/1.0" n="1788"/><ab xmlns="http://www.tei-c.org/ns/1.0" n="1789"/><ab xmlns="http://www.tei-c.org/ns/1.0" n="1790"/><ab xmlns="http://www.tei-c.org/ns/1.0" n="1791"/><ab xmlns="http://www.tei-c.org/ns/1.0" n="1792"/><ab xmlns="http://www.tei-c.org/ns/1.0" n="1793"/><ab xmlns="http://www.tei-c.org/ns/1.0" n="1794"/><ab xmlns="http://www.tei-c.org/ns/1.0" n="1795"/><ab xmlns="http://www.tei-c.org/ns/1.0" n="1796"/><ab xmlns="http://www.tei-c.org/ns/1.0" n="1797"/><ab xmlns="http://www.tei-c.org/ns/1.0" n="1798"/><ab xmlns="http://www.tei-c.org/ns/1.0" n="1799"/><ab xmlns="http://www.tei-c.org/ns/1.0" n="1800"/><ab xmlns="http://www.tei-c.org/ns/1.0" n="1801"/><ab xmlns="http://www.tei-c.org/ns/1.0" n="1802"/><ab xmlns="http://www.tei-c.org/ns/1.0" n="1803"/><ab xmlns="http://www.tei-c.org/ns/1.0" n="1804"/><ab xmlns="http://www.tei-c.org/ns/1.0" n="1805"/><ab xmlns="http://www.tei-c.org/ns/1.0" n="1806"/><ab xmlns="http://www.tei-c.org/ns/1.0" n="1807"/><ab xmlns="http://www.tei-c.org/ns/1.0" n="1808"/><ab xmlns="http://www.tei-c.org/ns/1.0" n="1809"/><ab xmlns="http://www.tei-c.org/ns/1.0" n="1810"/><ab xmlns="http://www.tei-c.org/ns/1.0" n="1811"/><ab xmlns="http://www.tei-c.org/ns/1.0" n="1812"/><ab xmlns="http://www.tei-c.org/ns/1.0" n="1813"/><ab xmlns="http://www.tei-c.org/ns/1.0" n="1814"/><ab xmlns="http://www.tei-c.org/ns/1.0" n="1815"/><ab xmlns="http://www.tei-c.org/ns/1.0" n="1816"/><ab xmlns="http://www.tei-c.org/ns/1.0" n="1817"/><ab xmlns="http://www.tei-c.org/ns/1.0" n="1818"/><ab xmlns="http://www.tei-c.org/ns/1.0" n="1819"/><ab xmlns="http://www.tei-c.org/ns/1.0" n="1820"/><ab xmlns="http://www.tei-c.org/ns/1.0" n="1821"/><ab xmlns="http://www.tei-c.org/ns/1.0" n="1822"/><ab xmlns="http://www.tei-c.org/ns/1.0" n="1823"/><ab xmlns="http://www.tei-c.org/ns/1.0" n="1824"/><ab xmlns="http://www.tei-c.org/ns/1.0" n="1825"/><ab xmlns="http://www.tei-c.org/ns/1.0" n="1826"/><ab xmlns="http://www.tei-c.org/ns/1.0" n="1827"/><ab xmlns="http://www.tei-c.org/ns/1.0" n="1828"/><ab xmlns="http://www.tei-c.org/ns/1.0" n="1829"/><ab xmlns="http://www.tei-c.org/ns/1.0" n="1830"><date xmlns="http://www.tei-c.org/ns/1.0" when="1830-07-17" n="notVenue" type="ah"/></ab><ab xmlns="http://www.tei-c.org/ns/1.0" n="1831"><date xmlns="http://www.tei-c.org/ns/1.0" when="1831-03-16" n="notVenue" type="ah"/></ab><ab xmlns="http://www.tei-c.org/ns/1.0" n="1832"/><ab xmlns="http://www.tei-c.org/ns/1.0" n="1833"><date xmlns="http://www.tei-c.org/ns/1.0" when="1833-01-01" n="notVenue" type="ah"/><date xmlns="http://www.tei-c.org/ns/1.0" when="1833-08-15" n="notVenue" type="ah"/></ab><ab xmlns="http://www.tei-c.org/ns/1.0" n="1834"/><ab xmlns="http://www.tei-c.org/ns/1.0" n="1835"><date xmlns="http://www.tei-c.org/ns/1.0" when="1835-03-09" n="notVenue" type="ah"/></ab><ab xmlns="http://www.tei-c.org/ns/1.0" n="1836"/></ab></person></listPerson>