<?xml version="1.0" encoding="UTF-8"?><listPerson xmlns="http://www.tei-c.org/ns/1.0"><person xmlns="http://www.tei-c.org/ns/1.0" xml:id="SHE04" sex="1"><persName xmlns="http://www.tei-c.org/ns/1.0"><forename xmlns="http://www.tei-c.org/ns/1.0">Richard Brinsley</forename><surname xmlns="http://www.tei-c.org/ns/1.0">Sheridan</surname><addName xmlns="http://www.tei-c.org/ns/1.0"/></persName><birth xmlns="http://www.tei-c.org/ns/1.0" notBefore="1751-09" notAfter="1751-10"><placeName xmlns="http://www.tei-c.org/ns/1.0">Ireland</placeName></birth><death xmlns="http://www.tei-c.org/ns/1.0" when="1816-07-07"/><occupation xmlns="http://www.tei-c.org/ns/1.0">playwright</occupation><occupation xmlns="http://www.tei-c.org/ns/1.0">politician</occupation><note xmlns="http://www.tei-c.org/ns/1.0" type="editorial"><p xmlns="http://www.tei-c.org/ns/1.0">Richard Brinsley Sheridan was an Irish born dramatist who achieved considerable success on
      the stage with his play <title xmlns="http://www.tei-c.org/ns/1.0">The Rivals</title> in 1775. Sheridan subsequetly became close
      to the whigs and was elected to Parliament in 1780. Godwin met Sheridan early in the 1780s and
      wrote for Sheridan's <title xmlns="http://www.tei-c.org/ns/1.0">Political Herald</title>.  He had intermittent contact subsequently, seeking 
      Sheridan's advice and support in the writing and prodouction of his tragedies.</p><p xmlns="http://www.tei-c.org/ns/1.0">Godwin records his death.</p></note><bibl xmlns="http://www.tei-c.org/ns/1.0" type="other"><title xmlns="http://www.tei-c.org/ns/1.0">DNB</title>.</bibl><ab xmlns="http://www.tei-c.org/ns/1.0" type="appearancesInDiary"><ab xmlns="http://www.tei-c.org/ns/1.0" n="1788"><date xmlns="http://www.tei-c.org/ns/1.0" when="1788-06-03" n="notVenue" type="ah"/><date xmlns="http://www.tei-c.org/ns/1.0" when="1788-06-03" n="notVenue" type="ah"/></ab><ab xmlns="http://www.tei-c.org/ns/1.0" n="1789"/><ab xmlns="http://www.tei-c.org/ns/1.0" n="1790"><date xmlns="http://www.tei-c.org/ns/1.0" when="1790-05-10" n="venue" type="ah"/><date xmlns="http://www.tei-c.org/ns/1.0" when="1790-07-14" n="notVenue" type="ah"/></ab><ab xmlns="http://www.tei-c.org/ns/1.0" n="1791"><date xmlns="http://www.tei-c.org/ns/1.0" when="1791-04-29" n="notVenue" type="ah"/></ab><ab xmlns="http://www.tei-c.org/ns/1.0" n="1792"><date xmlns="http://www.tei-c.org/ns/1.0" when="1792-02-13" n="notVenue" type="ah"/></ab><ab xmlns="http://www.tei-c.org/ns/1.0" n="1793"><date xmlns="http://www.tei-c.org/ns/1.0" when="1793-02-27" n="notVenue" type="ah"/><date xmlns="http://www.tei-c.org/ns/1.0" when="1793-03-04" n="notVenue" type="ah"/><date xmlns="http://www.tei-c.org/ns/1.0" when="1793-04-20" n="notVenue" type="ah"/><date xmlns="http://www.tei-c.org/ns/1.0" when="1793-11-09" n="notVenue" type="ah"/></ab><ab xmlns="http://www.tei-c.org/ns/1.0" n="1794"/><ab xmlns="http://www.tei-c.org/ns/1.0" n="1795"><date xmlns="http://www.tei-c.org/ns/1.0" when="1795-10-11" n="notVenue" type="ah"/></ab><ab xmlns="http://www.tei-c.org/ns/1.0" n="1796"><date xmlns="http://www.tei-c.org/ns/1.0" when="1796-04-28" n="notVenue" type="ah"/></ab><ab xmlns="http://www.tei-c.org/ns/1.0" n="1797"/><ab xmlns="http://www.tei-c.org/ns/1.0" n="1798"><date xmlns="http://www.tei-c.org/ns/1.0" when="1798-12-30" n="venue" type="ah"/></ab><ab xmlns="http://www.tei-c.org/ns/1.0" n="1799"><date xmlns="http://www.tei-c.org/ns/1.0" when="1799-02-21" n="notVenue" type="ah"/><date xmlns="http://www.tei-c.org/ns/1.0" when="1799-03-16" n="venue" type="nah"/><date xmlns="http://www.tei-c.org/ns/1.0" when="1799-03-18" n="venue" type="ah"/><date xmlns="http://www.tei-c.org/ns/1.0" when="1799-03-23" n="venue" type="nah"/><date xmlns="http://www.tei-c.org/ns/1.0" when="1799-03-29" n="venue" type="ah"/><date xmlns="http://www.tei-c.org/ns/1.0" when="1799-04-15" n="venue" type="nah"/><date xmlns="http://www.tei-c.org/ns/1.0" when="1799-04-16" n="venue" type="ah"/><date xmlns="http://www.tei-c.org/ns/1.0" when="1799-05-27" n="notVenue" type="ah"/><date xmlns="http://www.tei-c.org/ns/1.0" when="1799-06-03" n="venue" type="nah"/><date xmlns="http://www.tei-c.org/ns/1.0" when="1799-06-10" n="venue" type="nah"/><date xmlns="http://www.tei-c.org/ns/1.0" when="1799-06-17" n="venue" type="nah"/><date xmlns="http://www.tei-c.org/ns/1.0" when="1799-07-11" n="venue" type="nah"/><date xmlns="http://www.tei-c.org/ns/1.0" when="1799-07-13" n="venue" type="ah"/><date xmlns="http://www.tei-c.org/ns/1.0" when="1799-07-25" n="venue" type="nah"/><date xmlns="http://www.tei-c.org/ns/1.0" when="1799-10-27" n="notVenue" type="ah"/></ab><ab xmlns="http://www.tei-c.org/ns/1.0" n="1800"><date xmlns="http://www.tei-c.org/ns/1.0" when="1800-05-13" n="notVenue" type="ah"/><date xmlns="http://www.tei-c.org/ns/1.0" when="1800-11-05" n="notVenue" type="ah"/></ab><ab xmlns="http://www.tei-c.org/ns/1.0" n="1801"><date xmlns="http://www.tei-c.org/ns/1.0" when="1801-01-18" n="notVenue" type="ah"/></ab><ab xmlns="http://www.tei-c.org/ns/1.0" n="1802"><date xmlns="http://www.tei-c.org/ns/1.0" when="1802-01-08" n="notVenue" type="ah"/></ab><ab xmlns="http://www.tei-c.org/ns/1.0" n="1803"/><ab xmlns="http://www.tei-c.org/ns/1.0" n="1804"><date xmlns="http://www.tei-c.org/ns/1.0" when="1804-04-01" n="notVenue" type="ah"/><date xmlns="http://www.tei-c.org/ns/1.0" when="1804-12-31" n="notVenue" type="ah"/></ab><ab xmlns="http://www.tei-c.org/ns/1.0" n="1805"/><ab xmlns="http://www.tei-c.org/ns/1.0" n="1806"><date xmlns="http://www.tei-c.org/ns/1.0" when="1806-02-17" n="notVenue" type="ah"/><date xmlns="http://www.tei-c.org/ns/1.0" when="1806-03-12" n="notVenue" type="ah"/></ab><ab xmlns="http://www.tei-c.org/ns/1.0" n="1807"><date xmlns="http://www.tei-c.org/ns/1.0" when="1807-10-24" n="notVenue" type="ah"/><date xmlns="http://www.tei-c.org/ns/1.0" when="1807-10-31" n="notVenue" type="ah"/><date xmlns="http://www.tei-c.org/ns/1.0" when="1807-11-09" n="notVenue" type="ah"/></ab><ab xmlns="http://www.tei-c.org/ns/1.0" n="1808"/><ab xmlns="http://www.tei-c.org/ns/1.0" n="1809"/><ab xmlns="http://www.tei-c.org/ns/1.0" n="1810"/><ab xmlns="http://www.tei-c.org/ns/1.0" n="1811"/><ab xmlns="http://www.tei-c.org/ns/1.0" n="1812"/><ab xmlns="http://www.tei-c.org/ns/1.0" n="1813"/><ab xmlns="http://www.tei-c.org/ns/1.0" n="1814"/><ab xmlns="http://www.tei-c.org/ns/1.0" n="1815"/><ab xmlns="http://www.tei-c.org/ns/1.0" n="1816"><date xmlns="http://www.tei-c.org/ns/1.0" when="1816-07-07" n="notVenue" type="ah"/><date xmlns="http://www.tei-c.org/ns/1.0" when="1816-07-12" n="notVenue" type="ah"/><date xmlns="http://www.tei-c.org/ns/1.0" when="1816-07-13" n="notVenue" type="ah"/><date xmlns="http://www.tei-c.org/ns/1.0" when="1816-07-15" n="notVenue" type="ah"/></ab><ab xmlns="http://www.tei-c.org/ns/1.0" n="1817"/><ab xmlns="http://www.tei-c.org/ns/1.0" n="1818"/><ab xmlns="http://www.tei-c.org/ns/1.0" n="1819"/><ab xmlns="http://www.tei-c.org/ns/1.0" n="1820"/><ab xmlns="http://www.tei-c.org/ns/1.0" n="1821"/><ab xmlns="http://www.tei-c.org/ns/1.0" n="1822"/><ab xmlns="http://www.tei-c.org/ns/1.0" n="1823"/><ab xmlns="http://www.tei-c.org/ns/1.0" n="1824"/><ab xmlns="http://www.tei-c.org/ns/1.0" n="1825"/><ab xmlns="http://www.tei-c.org/ns/1.0" n="1826"/><ab xmlns="http://www.tei-c.org/ns/1.0" n="1827"/><ab xmlns="http://www.tei-c.org/ns/1.0" n="1828"/><ab xmlns="http://www.tei-c.org/ns/1.0" n="1829"/><ab xmlns="http://www.tei-c.org/ns/1.0" n="1830"/><ab xmlns="http://www.tei-c.org/ns/1.0" n="1831"/><ab xmlns="http://www.tei-c.org/ns/1.0" n="1832"/><ab xmlns="http://www.tei-c.org/ns/1.0" n="1833"/><ab xmlns="http://www.tei-c.org/ns/1.0" n="1834"/><ab xmlns="http://www.tei-c.org/ns/1.0" n="1835"/><ab xmlns="http://www.tei-c.org/ns/1.0" n="1836"/></ab></person></listPerson>